multiagentx/__init__.py
multiagentx/agent.py
multiagentx/group.py
multiagentx/group_planner.py
multiagentx/memory.py
multiagentx/planner.py
multiagentx/play.py
multiagentx/protocol.py
multiagentx/utilities/logger.py
multiagentx/utilities/printer.py
multiagentx/utilities/tools.py
multiagentx/utilities/utils.py
multiagentx-0.1.10.dist-info/LICENSE
multiagentx-0.1.10.dist-info/METADATA
multiagentx-0.1.10.dist-info/WHEEL
multiagentx-0.1.10.dist-info/top_level.txt
multiagentx-0.1.10.dist-info/RECORD
