Metadata-Version: 2.2
Name: multiagentx
Version: 0.1.10
Summary: multi agent framework
Author-email: ZJun <zhangjun310@live.com>
License: MIT License
Project-URL: Repository, https://github.com/ZJCODE/multiagentx
Classifier: Programming Language :: Python :: 3
Classifier: License :: OSI Approved :: MIT License
Classifier: Operating System :: OS Independent
Requires-Python: >=3.10
License-File: LICENSE
Requires-Dist: fastapi
Requires-Dist: requests
Requires-Dist: beautifulsoup4
Requires-Dist: pyyaml
Requires-Dist: chromadb
Requires-Dist: duckduckgo_search
Requires-Dist: openai
Requires-Dist: tavily-python
Requires-Dist: graphviz
Requires-Dist: python-dotenv
Requires-Dist: tenacity
